{
  "acta_url": "https://www.fcf.cat/acta/2526/futbol-11/lliga-elit/grup-1/elit/horta-uat-a/1cat/santfeliuenc-fc-a",
  "date": "11-04-2026",
  "score": "2025-2026",
  "home": {
    "name": "HORTA, U.AT. A",
    "starters": [
      {
        "dorsal": 1,
        "name": "LECUMBERRI ARTETA, MIKEL",
        "player_id": "25940953",
        "player_url": "https://www.fcf.cat/jugador/2526/futbol-11/lliga-elit/grup-1/54322937/25940953"
      },
      {
        "dorsal": 2,
        "name": "AREGALL GUILLEN, VICTOR",
        "player_id": "18487039",
        "player_url": "https://www.fcf.cat/jugador/2526/futbol-11/lliga-elit/grup-1/54322937/18487039"
      },
      {
        "dorsal": 3,
        "name": "HOMEDES DE LA FUENTE, SAMUEL",
        "player_id": "726659",
        "player_url": "https://www.fcf.cat/jugador/2526/futbol-11/lliga-elit/grup-1/54322937/726659"
      },
      {
        "dorsal": 4,
        "name": "JOSA LEVRATTO, GUILLEM",
        "player_id": "40663605",
        "player_url": "https://www.fcf.cat/jugador/2526/futbol-11/lliga-elit/grup-1/54322937/40663605"
      },
      {
        "dorsal": 5,
        "name": "NOGALES ROVIRA, DAVID",
        "player_id": "733161",
        "player_url": "https://www.fcf.cat/jugador/2526/futbol-11/lliga-elit/grup-1/54322937/733161"
      },
      {
        "dorsal": 6,
        "name": "RAMIREZ GALLEGO, MARC",
        "player_id": "18475149",
        "player_url": "https://www.fcf.cat/jugador/2526/futbol-11/lliga-elit/grup-1/54322937/18475149"
      },
      {
        "dorsal": 10,
        "name": "VIVES LUQUE, JOAN",
        "player_id": "638998",
        "player_url": "https://www.fcf.cat/jugador/2526/futbol-11/lliga-elit/grup-1/54322937/638998"
      },
      {
        "dorsal": 11,
        "name": "MONTESINOS SOLE, JORDI",
        "player_id": "18473908",
        "player_url": "https://www.fcf.cat/jugador/2526/futbol-11/lliga-elit/grup-1/54322937/18473908"
      },
      {
        "dorsal": 15,
        "name": "CIFUENTES PELAEZ, RUBEN",
        "player_id": "717530",
        "player_url": "https://www.fcf.cat/jugador/2526/futbol-11/lliga-elit/grup-1/54322937/717530"
      },
      {
        "dorsal": 16,
        "name": "PEDROL PALMADA, GERARD",
        "player_id": "731234",
        "player_url": "https://www.fcf.cat/jugador/2526/futbol-11/lliga-elit/grup-1/54322937/731234"
      },
      {
        "dorsal": 24,
        "name": "VILLAGRASA JIMENEZ, BRUNO",
        "player_id": "669936",
        "player_url": "https://www.fcf.cat/jugador/2526/futbol-11/lliga-elit/grup-1/54322937/669936"
      }
    ],
    "bench": [
      {
        "dorsal": 7,
        "name": "BABIA , HAITAM",
        "player_id": "774388",
        "player_url": "https://www.fcf.cat/jugador/2526/futbol-11/lliga-elit/grup-1/54322937/774388"
      },
      {
        "dorsal": 12,
        "name": "ARAGALL PUIGVERT, JORDI",
        "player_id": "15657367",
        "player_url": "https://www.fcf.cat/jugador/2526/futbol-11/lliga-elit/grup-1/54322937/15657367"
      },
      {
        "dorsal": 13,
        "name": "RODRIGUEZ PIQUERAS, LEON",
        "player_id": "38238071",
        "player_url": "https://www.fcf.cat/jugador/2526/futbol-11/lliga-elit/grup-1/54322937/38238071"
      },
      {
        "dorsal": 14,
        "name": "HAMAD , ABDUL-MOUATY",
        "player_id": "57345634",
        "player_url": "https://www.fcf.cat/jugador/2526/futbol-11/lliga-elit/grup-1/54322937/57345634"
      },
      {
        "dorsal": 17,
        "name": "COLY , PAPE OUMAR SARR",
        "player_id": "39311605",
        "player_url": "https://www.fcf.cat/jugador/2526/futbol-11/lliga-elit/grup-1/54322937/39311605"
      },
      {
        "dorsal": 19,
        "name": "TOURAY , FABAKARY",
        "player_id": "52100669",
        "player_url": "https://www.fcf.cat/jugador/2526/futbol-11/lliga-elit/grup-1/54322937/52100669"
      },
      {
        "dorsal": 20,
        "name": "VALVERDE MILLAN, JUAN",
        "player_id": "15337130",
        "player_url": "https://www.fcf.cat/jugador/2526/futbol-11/lliga-elit/grup-1/54322937/15337130"
      },
      {
        "dorsal": 22,
        "name": "KOUBISS AJOUB, ALI",
        "player_id": "15654695",
        "player_url": "https://www.fcf.cat/jugador/2526/futbol-11/lliga-elit/grup-1/54322937/15654695"
      },
      {
        "dorsal": 23,
        "name": "VALENTÍ SOLER CABOT, ENRIQUE",
        "player_id": "24255628",
        "player_url": "https://www.fcf.cat/jugador/2526/futbol-11/lliga-elit/grup-1/54322937/24255628"
      }
    ],
    "substitutions": [
      {
        "minute": 53,
        "out": {
          "dorsal": 15,
          "name": "CIFUENTES PELAEZ, RUBEN",
          "player_id": "717530"
        },
        "in": {
          "dorsal": 17,
          "name": "COLY , PAPE OUMAR SARR",
          "player_id": "39311605"
        }
      },
      {
        "minute": 53,
        "out": {
          "dorsal": 10,
          "name": "VIVES LUQUE, JOAN",
          "player_id": "638998"
        },
        "in": {
          "dorsal": 20,
          "name": "VALVERDE MILLAN, JUAN",
          "player_id": "15337130"
        }
      },
      {
        "minute": 76,
        "out": {
          "dorsal": 5,
          "name": "NOGALES ROVIRA, DAVID",
          "player_id": "733161"
        },
        "in": {
          "dorsal": 22,
          "name": "KOUBISS AJOUB, ALI",
          "player_id": "15654695"
        }
      },
      {
        "minute": 80,
        "out": {
          "dorsal": 11,
          "name": "MONTESINOS SOLE, JORDI",
          "player_id": "18473908"
        },
        "in": {
          "dorsal": 19,
          "name": "TOURAY , FABAKARY",
          "player_id": "52100669"
        }
      },
      {
        "minute": 82,
        "out": {
          "dorsal": 16,
          "name": "PEDROL PALMADA, GERARD",
          "player_id": "731234"
        },
        "in": {
          "dorsal": 14,
          "name": "HAMAD , ABDUL-MOUATY",
          "player_id": "57345634"
        }
      }
    ],
    "cards": []
  },
  "away": {
    "name": "SANTFELIUENC, F.C. A",
    "starters": [
      {
        "dorsal": 13,
        "name": "CASAMAYOR CONTEL, ANTONIO",
        "player_id": "900006824",
        "player_url": "https://www.fcf.cat/jugador/2526/futbol-11/lliga-elit/grup-1/54322937/900006824"
      },
      {
        "dorsal": 3,
        "name": "VILLEGAS SANTOS, ALBERT",
        "player_id": "744127",
        "player_url": "https://www.fcf.cat/jugador/2526/futbol-11/lliga-elit/grup-1/54322937/744127"
      },
      {
        "dorsal": 4,
        "name": "GARCÍA NACARINO, VÍCTOR",
        "player_id": "675104",
        "player_url": "https://www.fcf.cat/jugador/2526/futbol-11/lliga-elit/grup-1/54322937/675104"
      },
      {
        "dorsal": 6,
        "name": "VARESE NAFA, ANDRES",
        "player_id": "53848832",
        "player_url": "https://www.fcf.cat/jugador/2526/futbol-11/lliga-elit/grup-1/54322937/53848832"
      },
      {
        "dorsal": 7,
        "name": "MENDEZ GIRALDEZ, IVAN",
        "player_id": "701209",
        "player_url": "https://www.fcf.cat/jugador/2526/futbol-11/lliga-elit/grup-1/54322937/701209"
      },
      {
        "dorsal": 8,
        "name": "CARBONELL GIL, MARC",
        "player_id": "746568",
        "player_url": "https://www.fcf.cat/jugador/2526/futbol-11/lliga-elit/grup-1/54322937/746568"
      },
      {
        "dorsal": 10,
        "name": "FERNÁNDEZ FERNÁNDEZ, HÉCTOR",
        "player_id": "699148",
        "player_url": "https://www.fcf.cat/jugador/2526/futbol-11/lliga-elit/grup-1/54322937/699148"
      },
      {
        "dorsal": 12,
        "name": "CARESIA MESA, PAU",
        "player_id": "7001966",
        "player_url": "https://www.fcf.cat/jugador/2526/futbol-11/lliga-elit/grup-1/54322937/7001966"
      },
      {
        "dorsal": 16,
        "name": "OLAECHEA MARTÍNEZ, FRANCESC XAVIER",
        "player_id": "15169415",
        "player_url": "https://www.fcf.cat/jugador/2526/futbol-11/lliga-elit/grup-1/54322937/15169415"
      },
      {
        "dorsal": 17,
        "name": "AVILES DIAZ, ALEJANDRO",
        "player_id": "748540",
        "player_url": "https://www.fcf.cat/jugador/2526/futbol-11/lliga-elit/grup-1/54322937/748540"
      },
      {
        "dorsal": 22,
        "name": "CASARES ALGUACIL, MARC",
        "player_id": "18579866",
        "player_url": "https://www.fcf.cat/jugador/2526/futbol-11/lliga-elit/grup-1/54322937/18579866"
      }
    ],
    "bench": [
      {
        "dorsal": 1,
        "name": "VAZQUEZ ALONSO, MARC",
        "player_id": "15325597",
        "player_url": "https://www.fcf.cat/jugador/2526/futbol-11/lliga-elit/grup-1/54322937/15325597"
      },
      {
        "dorsal": 2,
        "name": "HERVIAS MARTINEZ, MARIO",
        "player_id": "750880",
        "player_url": "https://www.fcf.cat/jugador/2526/futbol-11/lliga-elit/grup-1/54322937/750880"
      },
      {
        "dorsal": 9,
        "name": "ALVAREZ CABO, SAUL",
        "player_id": "15180376",
        "player_url": "https://www.fcf.cat/jugador/2526/futbol-11/lliga-elit/grup-1/54322937/15180376"
      },
      {
        "dorsal": 11,
        "name": "MATEO QUEJIGO, ELOI",
        "player_id": "750063",
        "player_url": "https://www.fcf.cat/jugador/2526/futbol-11/lliga-elit/grup-1/54322937/750063"
      },
      {
        "dorsal": 18,
        "name": "RODRIGUEZ JIMENEZ, CHRISTIAN",
        "player_id": "723132",
        "player_url": "https://www.fcf.cat/jugador/2526/futbol-11/lliga-elit/grup-1/54322937/723132"
      },
      {
        "dorsal": 19,
        "name": "HONORATO TORREJON, KILIAN",
        "player_id": "709497",
        "player_url": "https://www.fcf.cat/jugador/2526/futbol-11/lliga-elit/grup-1/54322937/709497"
      },
      {
        "dorsal": 21,
        "name": "GUILLEM ARMADA, SAUL",
        "player_id": "15173121",
        "player_url": "https://www.fcf.cat/jugador/2526/futbol-11/lliga-elit/grup-1/54322937/15173121"
      },
      {
        "dorsal": 23,
        "name": "DURAN MANZANILLA, HUGO",
        "player_id": "20038387",
        "player_url": "https://www.fcf.cat/jugador/2526/futbol-11/lliga-elit/grup-1/54322937/20038387"
      },
      {
        "dorsal": 24,
        "name": "SADURNI FABRELLAS, JOSEP",
        "player_id": "19891478",
        "player_url": "https://www.fcf.cat/jugador/2526/futbol-11/lliga-elit/grup-1/54322937/19891478"
      }
    ],
    "substitutions": [
      {
        "minute": 29,
        "out": {
          "dorsal": 6,
          "name": "VARESE NAFA, ANDRES",
          "player_id": "53848832"
        },
        "in": {
          "dorsal": 18,
          "name": "RODRIGUEZ JIMENEZ, CHRISTIAN",
          "player_id": "723132"
        }
      },
      {
        "minute": 29,
        "out": {
          "dorsal": 16,
          "name": "OLAECHEA MARTÍNEZ, FRANCESC XAVIER",
          "player_id": "15169415"
        },
        "in": {
          "dorsal": 21,
          "name": "GUILLEM ARMADA, SAUL",
          "player_id": "15173121"
        }
      },
      {
        "minute": 46,
        "out": {
          "dorsal": 17,
          "name": "AVILES DIAZ, ALEJANDRO",
          "player_id": "748540"
        },
        "in": {
          "dorsal": 9,
          "name": "ALVAREZ CABO, SAUL",
          "player_id": "15180376"
        }
      },
      {
        "minute": 53,
        "out": {
          "dorsal": 7,
          "name": "MENDEZ GIRALDEZ, IVAN",
          "player_id": "701209"
        },
        "in": {
          "dorsal": 19,
          "name": "HONORATO TORREJON, KILIAN",
          "player_id": "709497"
        }
      },
      {
        "minute": 76,
        "out": {
          "dorsal": 10,
          "name": "FERNÁNDEZ FERNÁNDEZ, HÉCTOR",
          "player_id": "699148"
        },
        "in": {
          "dorsal": 2,
          "name": "HERVIAS MARTINEZ, MARIO",
          "player_id": "750880"
        }
      },
      {
        "minute": 88,
        "out": {
          "dorsal": 4,
          "name": "GARCÍA NACARINO, VÍCTOR",
          "player_id": "675104"
        },
        "in": {
          "dorsal": 11,
          "name": "MATEO QUEJIGO, ELOI",
          "player_id": "750063"
        }
      },
      {
        "minute": 88,
        "out": {
          "dorsal": 8,
          "name": "CARBONELL GIL, MARC",
          "player_id": "746568"
        },
        "in": {
          "dorsal": 23,
          "name": "DURAN MANZANILLA, HUGO",
          "player_id": "20038387"
        }
      }
    ],
    "cards": []
  },
  "goals": [
    {
      "score_after": "1 - 0",
      "scorer": "MONTESINOS SOLE, JORDI",
      "scorer_id": "18473908",
      "minute": 10,
      "type": "normal"
    },
    {
      "score_after": "2 - 0",
      "scorer": "CIFUENTES PELAEZ, RUBEN",
      "scorer_id": "717530",
      "minute": 12,
      "type": "normal"
    },
    {
      "score_after": "3 - 0",
      "scorer": "NOGALES ROVIRA, DAVID",
      "scorer_id": "733161",
      "minute": 16,
      "type": "normal"
    },
    {
      "score_after": "3 - 1",
      "scorer": "CASARES ALGUACIL, MARC",
      "scorer_id": "18579866",
      "minute": 48,
      "type": "normal"
    }
  ],
  "jornada": 25
}