{
  "acta_url": "https://www.fcf.cat/acta/2526/futbol-11/lliga-elit/grup-1/elit/atletic-sant-just-f-c-a/elit/castelldefels-ue-a",
  "date": "07-02-2026",
  "score": "2025-2026",
  "home": {
    "name": "ATLETIC SANT JUST . F. C. A",
    "starters": [
      {
        "dorsal": 13,
        "name": "LOPEZ LLORENS, VICTOR",
        "player_id": "15947526",
        "player_url": "https://www.fcf.cat/jugador/2526/futbol-11/lliga-elit/grup-1/54322937/15947526"
      },
      {
        "dorsal": 2,
        "name": "SABASTIAN , GODWIN JOHN",
        "player_id": "46878477",
        "player_url": "https://www.fcf.cat/jugador/2526/futbol-11/lliga-elit/grup-1/54322937/46878477"
      },
      {
        "dorsal": 4,
        "name": "PALACIOS CORRAL, IGNACIO",
        "player_id": "672478",
        "player_url": "https://www.fcf.cat/jugador/2526/futbol-11/lliga-elit/grup-1/54322937/672478"
      },
      {
        "dorsal": 6,
        "name": "GONZÁLEZ TARRUELLA, MARC",
        "player_id": "727840",
        "player_url": "https://www.fcf.cat/jugador/2526/futbol-11/lliga-elit/grup-1/54322937/727840"
      },
      {
        "dorsal": 9,
        "name": "GUMA CERQUEDA, JAN",
        "player_id": "38436012",
        "player_url": "https://www.fcf.cat/jugador/2526/futbol-11/lliga-elit/grup-1/54322937/38436012"
      },
      {
        "dorsal": 10,
        "name": "GONZALEZ OLLER, JAN ANTONI",
        "player_id": "722808",
        "player_url": "https://www.fcf.cat/jugador/2526/futbol-11/lliga-elit/grup-1/54322937/722808"
      },
      {
        "dorsal": 11,
        "name": "BEATTIE ORFILA, ERIK",
        "player_id": "15134055",
        "player_url": "https://www.fcf.cat/jugador/2526/futbol-11/lliga-elit/grup-1/54322937/15134055"
      },
      {
        "dorsal": 19,
        "name": "ARJONA SERRANO, PAU",
        "player_id": "750040",
        "player_url": "https://www.fcf.cat/jugador/2526/futbol-11/lliga-elit/grup-1/54322937/750040"
      },
      {
        "dorsal": 21,
        "name": "PEREZ PICON, DAVID",
        "player_id": "628784",
        "player_url": "https://www.fcf.cat/jugador/2526/futbol-11/lliga-elit/grup-1/54322937/628784"
      },
      {
        "dorsal": 22,
        "name": "PILAR DEL HOYO, JON",
        "player_id": "15706465",
        "player_url": "https://www.fcf.cat/jugador/2526/futbol-11/lliga-elit/grup-1/54322937/15706465"
      },
      {
        "dorsal": 24,
        "name": "SORROCHE CALLE, MARK",
        "player_id": "785098",
        "player_url": "https://www.fcf.cat/jugador/2526/futbol-11/lliga-elit/grup-1/54322937/785098"
      }
    ],
    "bench": [
      {
        "dorsal": 1,
        "name": "CRESPO YUNTA, GUILLERMO",
        "player_id": "15666684",
        "player_url": "https://www.fcf.cat/jugador/2526/futbol-11/lliga-elit/grup-1/54322937/15666684"
      },
      {
        "dorsal": 5,
        "name": "MONTES JIMENEZ, ALBERT",
        "player_id": "737323",
        "player_url": "https://www.fcf.cat/jugador/2526/futbol-11/lliga-elit/grup-1/54322937/737323"
      },
      {
        "dorsal": 8,
        "name": "RUIZ PIQUE, ARNAU",
        "player_id": "18632084",
        "player_url": "https://www.fcf.cat/jugador/2526/futbol-11/lliga-elit/grup-1/54322937/18632084"
      },
      {
        "dorsal": 12,
        "name": "SANCHEZ PLACENCIA, IVAN",
        "player_id": "15158482",
        "player_url": "https://www.fcf.cat/jugador/2526/futbol-11/lliga-elit/grup-1/54322937/15158482"
      },
      {
        "dorsal": 14,
        "name": "RABANAL VILLAR, ANIOL",
        "player_id": "637130",
        "player_url": "https://www.fcf.cat/jugador/2526/futbol-11/lliga-elit/grup-1/54322937/637130"
      },
      {
        "dorsal": 16,
        "name": "MELERO CALVO, UNAI",
        "player_id": "15544346",
        "player_url": "https://www.fcf.cat/jugador/2526/futbol-11/lliga-elit/grup-1/54322937/15544346"
      },
      {
        "dorsal": 17,
        "name": "GIL NAVARRO, JOEL",
        "player_id": "15550746",
        "player_url": "https://www.fcf.cat/jugador/2526/futbol-11/lliga-elit/grup-1/54322937/15550746"
      },
      {
        "dorsal": 23,
        "name": "BUERA NADAL, FERRAN",
        "player_id": "651174",
        "player_url": "https://www.fcf.cat/jugador/2526/futbol-11/lliga-elit/grup-1/54322937/651174"
      },
      {
        "dorsal": 25,
        "name": "SANCHEZ ERAZO, ALLAN MACCRAY",
        "player_id": "57736517",
        "player_url": "https://www.fcf.cat/jugador/2526/futbol-11/lliga-elit/grup-1/54322937/57736517"
      }
    ],
    "substitutions": [],
    "cards": []
  },
  "away": {
    "name": "CASTELLDEFELS, U.E. A",
    "starters": [
      {
        "dorsal": 13,
        "name": "GUTIÉRREZ ADAME, ADRIÀ",
        "player_id": "15596602",
        "player_url": "https://www.fcf.cat/jugador/2526/futbol-11/lliga-elit/grup-1/54322937/15596602"
      },
      {
        "dorsal": 3,
        "name": "PEÑAS ANDREU, ALEX",
        "player_id": "629565",
        "player_url": "https://www.fcf.cat/jugador/2526/futbol-11/lliga-elit/grup-1/54322937/629565"
      },
      {
        "dorsal": 5,
        "name": "ORTEGA RAMIREZ, IVAN",
        "player_id": "15588249",
        "player_url": "https://www.fcf.cat/jugador/2526/futbol-11/lliga-elit/grup-1/54322937/15588249"
      },
      {
        "dorsal": 7,
        "name": "DIAZ MENDOZA, ALEIX",
        "player_id": "648528",
        "player_url": "https://www.fcf.cat/jugador/2526/futbol-11/lliga-elit/grup-1/54322937/648528"
      },
      {
        "dorsal": 8,
        "name": "DEL CHICCA DORADO, HUGO",
        "player_id": "37920251",
        "player_url": "https://www.fcf.cat/jugador/2526/futbol-11/lliga-elit/grup-1/54322937/37920251"
      },
      {
        "dorsal": 11,
        "name": "GERBOLES PEREZ, MARIO",
        "player_id": "632224",
        "player_url": "https://www.fcf.cat/jugador/2526/futbol-11/lliga-elit/grup-1/54322937/632224"
      },
      {
        "dorsal": 12,
        "name": "MONTERO PRADAS, IKER",
        "player_id": "15765782",
        "player_url": "https://www.fcf.cat/jugador/2526/futbol-11/lliga-elit/grup-1/54322937/15765782"
      },
      {
        "dorsal": 14,
        "name": "GIBERT FUERTES, JOAN",
        "player_id": "668573",
        "player_url": "https://www.fcf.cat/jugador/2526/futbol-11/lliga-elit/grup-1/54322937/668573"
      },
      {
        "dorsal": 15,
        "name": "FAURA MARTINEZ, JOEL",
        "player_id": "15908749",
        "player_url": "https://www.fcf.cat/jugador/2526/futbol-11/lliga-elit/grup-1/54322937/15908749"
      },
      {
        "dorsal": 19,
        "name": "PARRA GARCIA, EDGAR",
        "player_id": "630390",
        "player_url": "https://www.fcf.cat/jugador/2526/futbol-11/lliga-elit/grup-1/54322937/630390"
      },
      {
        "dorsal": 24,
        "name": "VILLAVERDE GARCIA, KILIAN",
        "player_id": "40748333",
        "player_url": "https://www.fcf.cat/jugador/2526/futbol-11/lliga-elit/grup-1/54322937/40748333"
      }
    ],
    "bench": [
      {
        "dorsal": 1,
        "name": "FERRANDO RASO, ALEX",
        "player_id": "18475186",
        "player_url": "https://www.fcf.cat/jugador/2526/futbol-11/lliga-elit/grup-1/54322937/18475186"
      },
      {
        "dorsal": 2,
        "name": "MARTIN DURAN, JUAN ANTONIO",
        "player_id": "900009008",
        "player_url": "https://www.fcf.cat/jugador/2526/futbol-11/lliga-elit/grup-1/54322937/900009008"
      },
      {
        "dorsal": 6,
        "name": "GIMENO HERNÁNDEZ, ADRIÁN",
        "player_id": "629546",
        "player_url": "https://www.fcf.cat/jugador/2526/futbol-11/lliga-elit/grup-1/54322937/629546"
      },
      {
        "dorsal": 10,
        "name": "CANO JIMENEZ, CARLOS",
        "player_id": "633680",
        "player_url": "https://www.fcf.cat/jugador/2526/futbol-11/lliga-elit/grup-1/54322937/633680"
      },
      {
        "dorsal": 16,
        "name": "FERREIRA MOREIRA, JONATHAN",
        "player_id": "44279498",
        "player_url": "https://www.fcf.cat/jugador/2526/futbol-11/lliga-elit/grup-1/54322937/44279498"
      },
      {
        "dorsal": 18,
        "name": "LOPEZ GARCIA, DAVID",
        "player_id": "666246",
        "player_url": "https://www.fcf.cat/jugador/2526/futbol-11/lliga-elit/grup-1/54322937/666246"
      },
      {
        "dorsal": 20,
        "name": "MALDONADO MOYA, IZAN",
        "player_id": "727358",
        "player_url": "https://www.fcf.cat/jugador/2526/futbol-11/lliga-elit/grup-1/54322937/727358"
      },
      {
        "dorsal": 23,
        "name": "MATAMOROS SEGURA, JOEL",
        "player_id": "23168454",
        "player_url": "https://www.fcf.cat/jugador/2526/futbol-11/lliga-elit/grup-1/54322937/23168454"
      }
    ],
    "substitutions": [],
    "cards": []
  },
  "goals": [],
  "jornada": 18
}