{
  "acta_url": "https://www.fcf.cat/acta/2526/futbol-11/lliga-elit/grup-1/elit/san-mauro-ud-a/elit/castelldefels-ue-a",
  "date": "20-12-2025",
  "score": "2025-2026",
  "home": {
    "name": "SAN MAURO, U.D. A",
    "starters": [
      {
        "dorsal": 25,
        "name": "MARTÍNEZ BENÍTEZ, CALEB",
        "player_url": "https://www.fcf.cat/jugador/2526/futbol-11/lliga-elit/grup-1/54322937/727295"
      },
      {
        "dorsal": 4,
        "name": "MASEGOSA SOLÍS, ALBERT",
        "player_url": "https://www.fcf.cat/jugador/2526/futbol-11/lliga-elit/grup-1/54322937/676982"
      },
      {
        "dorsal": 5,
        "name": "GARCÍA GARCÍA, JAVIER",
        "player_url": "https://www.fcf.cat/jugador/2526/futbol-11/lliga-elit/grup-1/54322937/662263"
      },
      {
        "dorsal": 6,
        "name": "ENRIQUEZ DE LA ROSA, MARC",
        "player_url": "https://www.fcf.cat/jugador/2526/futbol-11/lliga-elit/grup-1/54322937/734626"
      },
      {
        "dorsal": 8,
        "name": "BENITO ALSINA, BERNAT",
        "player_url": "https://www.fcf.cat/jugador/2526/futbol-11/lliga-elit/grup-1/54322937/654350"
      },
      {
        "dorsal": 9,
        "name": "ESCAMILLA VAN DER DONK, ROGER",
        "player_url": "https://www.fcf.cat/jugador/2526/futbol-11/lliga-elit/grup-1/54322937/688137"
      },
      {
        "dorsal": 14,
        "name": "MAYMÓ BALLESTER, LLUC",
        "player_url": "https://www.fcf.cat/jugador/2526/futbol-11/lliga-elit/grup-1/54322937/15042061"
      },
      {
        "dorsal": 15,
        "name": "ESTEVE MEDINA, DANIEL",
        "player_url": "https://www.fcf.cat/jugador/2526/futbol-11/lliga-elit/grup-1/54322937/18769011"
      },
      {
        "dorsal": 17,
        "name": "ROMEU MARQUES, POL",
        "player_url": "https://www.fcf.cat/jugador/2526/futbol-11/lliga-elit/grup-1/54322937/18669938"
      },
      {
        "dorsal": 19,
        "name": "CAÑERO CARMONA, ALEX",
        "player_url": "https://www.fcf.cat/jugador/2526/futbol-11/lliga-elit/grup-1/54322937/31990626"
      },
      {
        "dorsal": 20,
        "name": "GULIAS AGUILERA, MARC",
        "player_url": "https://www.fcf.cat/jugador/2526/futbol-11/lliga-elit/grup-1/54322937/722851"
      }
    ],
    "bench": [
      {
        "dorsal": 3,
        "name": "NAVARRO , GUIDO ALCIDES",
        "player_url": "https://www.fcf.cat/jugador/2526/futbol-11/lliga-elit/grup-1/54322937/44354719"
      },
      {
        "dorsal": 7,
        "name": "ROSINÉS LÓPEZ, XAVIER",
        "player_url": "https://www.fcf.cat/jugador/2526/futbol-11/lliga-elit/grup-1/54322937/23069122"
      },
      {
        "dorsal": 11,
        "name": "BERENGUER ALONSO, ORIOL",
        "player_url": "https://www.fcf.cat/jugador/2526/futbol-11/lliga-elit/grup-1/54322937/19645275"
      },
      {
        "dorsal": 13,
        "name": "CLARAMUNT GONZALEZ, ADRIÀ",
        "player_url": "https://www.fcf.cat/jugador/2526/futbol-11/lliga-elit/grup-1/54322937/15643074"
      },
      {
        "dorsal": 16,
        "name": "SARSANEDAS CONTRERAS, JOAO",
        "player_url": "https://www.fcf.cat/jugador/2526/futbol-11/lliga-elit/grup-1/54322937/15549504"
      },
      {
        "dorsal": 18,
        "name": "MORENO ORDOÑEZ, DAVID",
        "player_url": "https://www.fcf.cat/jugador/2526/futbol-11/lliga-elit/grup-1/54322937/15089975"
      },
      {
        "dorsal": 22,
        "name": "PUCHE RODRÍGUEZ, FERRAN",
        "player_url": "https://www.fcf.cat/jugador/2526/futbol-11/lliga-elit/grup-1/54322937/15195656"
      },
      {
        "dorsal": 23,
        "name": "GUELL SANCHEZ, CARLES",
        "player_url": "https://www.fcf.cat/jugador/2526/futbol-11/lliga-elit/grup-1/54322937/7004960"
      }
    ],
    "substitutions": [
      {
        "minute": 68,
        "out": {
          "dorsal": 17,
          "name": "ROMEU MARQUES, POL"
        },
        "in": {
          "dorsal": 16,
          "name": "SARSANEDAS CONTRERAS, JOAO"
        }
      },
      {
        "minute": 68,
        "out": {
          "dorsal": 6,
          "name": "ENRIQUEZ DE LA ROSA, MARC"
        },
        "in": {
          "dorsal": 23,
          "name": "GUELL SANCHEZ, CARLES"
        }
      },
      {
        "minute": 88,
        "out": {
          "dorsal": 20,
          "name": "GULIAS AGUILERA, MARC"
        },
        "in": {
          "dorsal": 22,
          "name": "PUCHE RODRÍGUEZ, FERRAN"
        }
      }
    ],
    "cards": []
  },
  "away": {
    "name": "CASTELLDEFELS, U.E. A",
    "starters": [
      {
        "dorsal": 13,
        "name": "GUTIÉRREZ ADAME, ADRIÀ",
        "player_url": "https://www.fcf.cat/jugador/2526/futbol-11/lliga-elit/grup-1/54322937/15596602"
      },
      {
        "dorsal": 2,
        "name": "MARTIN DURAN, JUAN ANTONIO",
        "player_url": "https://www.fcf.cat/jugador/2526/futbol-11/lliga-elit/grup-1/54322937/900009008"
      },
      {
        "dorsal": 3,
        "name": "PEÑAS ANDREU, ALEX",
        "player_url": "https://www.fcf.cat/jugador/2526/futbol-11/lliga-elit/grup-1/54322937/629565"
      },
      {
        "dorsal": 6,
        "name": "GIMENO HERNÁNDEZ, ADRIÁN",
        "player_url": "https://www.fcf.cat/jugador/2526/futbol-11/lliga-elit/grup-1/54322937/629546"
      },
      {
        "dorsal": 9,
        "name": "POZUELO RIERA, ELOI",
        "player_url": "https://www.fcf.cat/jugador/2526/futbol-11/lliga-elit/grup-1/54322937/40602472"
      },
      {
        "dorsal": 11,
        "name": "GERBOLES PEREZ, MARIO",
        "player_url": "https://www.fcf.cat/jugador/2526/futbol-11/lliga-elit/grup-1/54322937/632224"
      },
      {
        "dorsal": 12,
        "name": "MONTERO PRADAS, IKER",
        "player_url": "https://www.fcf.cat/jugador/2526/futbol-11/lliga-elit/grup-1/54322937/15765782"
      },
      {
        "dorsal": 14,
        "name": "GIBERT FUERTES, JOAN",
        "player_url": "https://www.fcf.cat/jugador/2526/futbol-11/lliga-elit/grup-1/54322937/668573"
      },
      {
        "dorsal": 17,
        "name": "FRANCO CARRASCO, PABLO",
        "player_url": "https://www.fcf.cat/jugador/2526/futbol-11/lliga-elit/grup-1/54322937/663545"
      },
      {
        "dorsal": 19,
        "name": "PARRA GARCIA, EDGAR",
        "player_url": "https://www.fcf.cat/jugador/2526/futbol-11/lliga-elit/grup-1/54322937/630390"
      },
      {
        "dorsal": 24,
        "name": "VILLAVERDE GARCIA, KILIAN",
        "player_url": "https://www.fcf.cat/jugador/2526/futbol-11/lliga-elit/grup-1/54322937/40748333"
      }
    ],
    "bench": [
      {
        "dorsal": 1,
        "name": "FERRANDO RASO, ALEX",
        "player_url": "https://www.fcf.cat/jugador/2526/futbol-11/lliga-elit/grup-1/54322937/18475186"
      },
      {
        "dorsal": 7,
        "name": "RAMIREZ RUIZ, ENRIQUE",
        "player_url": "https://www.fcf.cat/jugador/2526/futbol-11/lliga-elit/grup-1/54322937/642498"
      },
      {
        "dorsal": 10,
        "name": "CANO JIMENEZ, CARLOS",
        "player_url": "https://www.fcf.cat/jugador/2526/futbol-11/lliga-elit/grup-1/54322937/633680"
      },
      {
        "dorsal": 15,
        "name": "FAURA MARTINEZ, JOEL",
        "player_url": "https://www.fcf.cat/jugador/2526/futbol-11/lliga-elit/grup-1/54322937/15908749"
      },
      {
        "dorsal": 16,
        "name": "FERREIRA MOREIRA, JONATHAN",
        "player_url": "https://www.fcf.cat/jugador/2526/futbol-11/lliga-elit/grup-1/54322937/44279498"
      },
      {
        "dorsal": 18,
        "name": "POUGET FLORIDO, MARC",
        "player_url": "https://www.fcf.cat/jugador/2526/futbol-11/lliga-elit/grup-1/54322937/735014"
      },
      {
        "dorsal": 20,
        "name": "MALDONADO MOYA, IZAN",
        "player_url": "https://www.fcf.cat/jugador/2526/futbol-11/lliga-elit/grup-1/54322937/727358"
      },
      {
        "dorsal": 21,
        "name": "DIAZ MENDOZA, ALEIX",
        "player_url": "https://www.fcf.cat/jugador/2526/futbol-11/lliga-elit/grup-1/54322937/648528"
      },
      {
        "dorsal": 23,
        "name": "MATAMOROS SEGURA, JOEL",
        "player_url": "https://www.fcf.cat/jugador/2526/futbol-11/lliga-elit/grup-1/54322937/23168454"
      }
    ],
    "substitutions": [
      {
        "minute": 46,
        "out": {
          "dorsal": 9,
          "name": "POZUELO RIERA, ELOI"
        },
        "in": {
          "dorsal": 20,
          "name": "MALDONADO MOYA, IZAN"
        }
      },
      {
        "minute": 68,
        "out": {
          "dorsal": 2,
          "name": "MARTIN DURAN, JUAN ANTONIO"
        },
        "in": {
          "dorsal": 16,
          "name": "FERREIRA MOREIRA, JONATHAN"
        }
      },
      {
        "minute": 68,
        "out": {
          "dorsal": 11,
          "name": "GERBOLES PEREZ, MARIO"
        },
        "in": {
          "dorsal": 18,
          "name": "POUGET FLORIDO, MARC"
        }
      },
      {
        "minute": 68,
        "out": {
          "dorsal": 17,
          "name": "FRANCO CARRASCO, PABLO"
        },
        "in": {
          "dorsal": 21,
          "name": "DIAZ MENDOZA, ALEIX"
        }
      },
      {
        "minute": 72,
        "out": {
          "dorsal": 24,
          "name": "VILLAVERDE GARCIA, KILIAN"
        },
        "in": {
          "dorsal": 10,
          "name": "CANO JIMENEZ, CARLOS"
        }
      },
      {
        "minute": 72,
        "out": {
          "dorsal": 19,
          "name": "PARRA GARCIA, EDGAR"
        },
        "in": {
          "dorsal": 15,
          "name": "FAURA MARTINEZ, JOEL"
        }
      },
      {
        "minute": 86,
        "out": {
          "dorsal": 14,
          "name": "GIBERT FUERTES, JOAN"
        },
        "in": {
          "dorsal": 7,
          "name": "RAMIREZ RUIZ, ENRIQUE"
        }
      }
    ],
    "cards": []
  },
  "goals": [
    {
      "score_after": "0 - 1",
      "scorer": "VILLAVERDE GARCIA, KILIAN",
      "minute": 31,
      "type": "normal"
    },
    {
      "score_after": "1 - 1",
      "scorer": "CAÑERO CARMONA, ALEX",
      "minute": 43,
      "type": "normal"
    },
    {
      "score_after": "1 - 2",
      "scorer": "MALDONADO MOYA, IZAN",
      "minute": 58,
      "type": "normal"
    },
    {
      "score_after": "1 - 3",
      "scorer": "DIAZ MENDOZA, ALEIX",
      "minute": 73,
      "type": "normal"
    }
  ],
  "jornada": 13
}